cicdwithtravis-1.1.data/data/answers/Answers.txt
cicdwithtravis-1.1.data/data/questions/Questions.txt
cicdwithtravis-1.1.data/data/topics/Topics.txt
qa/__init__.py
qa/app.py
qa/edit_distance.py
qa/parsedata.py
cicdwithtravis-1.1.dist-info/METADATA
cicdwithtravis-1.1.dist-info/WHEEL
cicdwithtravis-1.1.dist-info/entry_points.txt
cicdwithtravis-1.1.dist-info/top_level.txt
cicdwithtravis-1.1.dist-info/RECORD
