Metadata-Version: 2.1
Name: cicdwithtravis
Version: 1.1
Summary: A Python Flask NLP application with CICD in Travis CI
Home-page: https://github.com/axel-sirota/ci-cd-with-travis
Author: Axel Sirota
Author-email: axel.sirota@gmail.com
License: UNKNOWN
Keywords: travisci setuptools development
Platform: UNKNOWN
Classifier: Development Status :: 3 - Alpha
Classifier: Intended Audience :: Developers
Classifier: Topic :: Software Development :: Build Tools
Classifier: License :: OSI Approved :: MIT License
Classifier: Programming Language :: Python :: 3.6
Classifier: Programming Language :: Python :: 3.7
Classifier: Programming Language :: Python :: 3.8
Requires-Python: >=2.7, !=3.0.*, !=3.1.*, !=3.2.*, !=3.3.*, !=3.4.*, !=3.5.*, <4
